market_prices/__init__.py
market_prices/_version.py
market_prices/data.py
market_prices/daterange.py
market_prices/errors.py
market_prices/helpers.py
market_prices/intervals.py
market_prices/mptypes.py
market_prices/parsing.py
market_prices/pt.py
market_prices/prices/__init__.py
market_prices/prices/base.py
market_prices/prices/csv.py
market_prices/prices/yahoo.py
market_prices/prices/config/__init__.py
market_prices/prices/config/config_yahoo.py
market_prices/support/__init__.py
market_prices/support/tutorial_helpers.py
market_prices/utils/__init__.py
market_prices/utils/calendar_utils.py
market_prices/utils/general_utils.py
market_prices/utils/pandas_utils.py
market_prices-0.12.11.dist-info/licenses/LICENSE.txt
market_prices-0.12.11.dist-info/METADATA
market_prices-0.12.11.dist-info/WHEEL
market_prices-0.12.11.dist-info/top_level.txt
market_prices-0.12.11.dist-info/RECORD
