Metadata-Version: 2.4
Name: market-prices
Version: 0.12.11
Summary: Meaningful OHLCV datasets
Author: Marcus Read
Author-email: marcusaread.prog@proton.me
License-Expression: MIT
Project-URL: homepage, https://github.com/maread99/market_prices
Project-URL: documentation, https://github.com/maread99/market_prices/blob/master/docs/tutorials_docs.md
Project-URL: Issue Tracker, https://github.com/maread99/market_prices/issues
Project-URL: Source Code, https://github.com/maread99/market_prices
Keywords: finance,prices,historical-data,yahoo,investing,stocks,currencies,forex,crypto,etf,funds,bonds,commodities,indices
Classifier: Development Status :: 4 - Beta
Classifier: Intended Audience :: Developers
Classifier: Intended Audience :: Education
Classifier: Intended Audience :: Financial and Insurance Industry
Classifier: Intended Audience :: Science/Research
Classifier: Natural Language :: English
Classifier: Operating System :: OS Independent
Classifier: Programming Language :: Python
Classifier: Programming Language :: Python :: 3
Classifier: Programming Language :: Python :: 3 :: Only
Classifier: Programming Language :: Python :: 3.10
Classifier: Programming Language :: Python :: 3.11
Classifier: Programming Language :: Python :: 3.12
Classifier: Programming Language :: Python :: 3.13
Classifier: Programming Language :: Python :: Implementation :: CPython
Classifier: Topic :: Education
Classifier: Topic :: Office/Business :: Financial
Classifier: Topic :: Software Development :: Libraries :: Python Modules
Requires-Python: <4,>=3.10
License-File: LICENSE.txt
Requires-Dist: exchange_calendars
Requires-Dist: numpy
Requires-Dist: pandas
Requires-Dist: tzdata
Requires-Dist: valimp
Requires-Dist: yahooquery
Dynamic: license-file
